Workbook

Sheet Variable Information
A1: Variable | B1: Position | C1: Label | D1: WJP variable equivalent | E1: WJP label | F1: Match | G1: Notes | H1: " | I1: renaming
A2: respondentid | B2: 1 | C2: Respondent ID | D2: id | H2: =_xlfn.CONCAT("label var ",A2," ",$H$1,C2,$H$1) -> label var respondentid "Respondent ID"
A3: q11 | B3: 2 | C3: Q11. Gender. Do you identify as: | D3: gend | E3: gend | H3: =_xlfn.CONCAT("label var ",A3," ",$H$1,C3,$H$1) -> label var q11 "Q11. Gender. Do you identify as:" | I3: =_xlfn.CONCAT("rename ",A3," ",E3) -> rename q11 gend
A4: q03 | B4: 3 | C4: Q3. Age | D4: age | E4: age | H4: =_xlfn.CONCAT("label var ",A4," ",$H$1,C4,$H$1) -> label var q03 "Q3. Age" | I4: =_xlfn.CONCAT("rename ",A4," ",E4) -> rename q03 age
A5: q18 | B5: 4 | C5: Q18. Which of the following is the highest level of education or training you have completed? | D5: edu | E5: edu | H5: =_xlfn.CONCAT("label var ",A5," ",$H$1,C5,$H$1) -> label var q18 "Q18. Which of the following is the highest level of education or training you have completed?" | I5: =_xlfn.CONCAT("rename ",A5," ",E5) -> rename q18 edu
A6: education | B6: 5 | C6: Education | D6: edu | E6: edu_2 | G6: Recoded q18 1-4 as 1, 5-11 as 2 | H6: =_xlfn.CONCAT("label var ",A6," ",$H$1,C6,$H$1) -> label var education "Education" | I6: =_xlfn.CONCAT("rename ",A6," ",E6) -> rename education edu_2
A7: q17 | B7: 6 | C7: Q17. Which one of the following best describes your current situation? | D7: emp | E7: emp | H7: =_xlfn.CONCAT("label var ",A7," ",$H$1,C7,$H$1) -> label var q17 "Q17. Which one of the following best describes your current situation?" | I7: =_xlfn.CONCAT("rename ",A7," ",E7) -> rename q17 emp
A8: employment | B8: 7 | C8: Employment | D8: emp | E8: emp_2 | G8: Recoded q17 1=1, 2-9=2 | H8: =_xlfn.CONCAT("label var ",A8," ",$H$1,C8,$H$1) -> label var employment "Employment" | I8: =_xlfn.CONCAT("rename ",A8," ",E8) -> rename employment emp_2
A9: qsocialgrade | B9: 8 | C9: QSocialGrade. Please indicate which occupational group best describes the main earner in your household, or which group fits best. | D9: work | E9: work | H9: =_xlfn.CONCAT("label var ",A9," ",$H$1,C9,$H$1) -> label var qsocialgrade "QSocialGrade. Please indicate which occupational group best describes the main earner in your household, or which group fits best." | I9: =_xlfn.CONCAT("rename ",A9," ",E9) -> rename qsocialgrade work
A10: socialgrade | B10: 9 | C10: Social Grade | D10: work | E10: work_2 | G10: Some sort of grouping of QSocialGrade | H10: =_xlfn.CONCAT("label var ",A10," ",$H$1,C10,$H$1) -> label var socialgrade "Social Grade" | I10: =_xlfn.CONCAT("rename ",A10," ",E10) -> rename socialgrade work_2
A11: county | B11: 10 | C11: County. What is the name of the county where you currently live? | D11: ? | E11: county | H11: =_xlfn.CONCAT("label var ",A11," ",$H$1,C11,$H$1) -> label var county "County. What is the name of the county where you currently live?" | I11: =_xlfn.CONCAT("rename ",A11," ",E11) -> rename county county
A12: region | B12: 11 | C12: Region. | D12: country_code_nuts? | E12: region | H12: =_xlfn.CONCAT("label var ",A12," ",$H$1,C12,$H$1) -> label var region "Region." | I12: =_xlfn.CONCAT("rename ",A12," ",E12) -> rename region region
A13: q23_1_1 | B13: 12 | C13: Q23_1. Are you currently or previously have been in the past two years...? - A tenant | E13: tenant | H13: =_xlfn.CONCAT("label var ",A13," ",$H$1,C13,$H$1) -> label var q23_1_1 "Q23_1. Are you currently or previously have been in the past two years...? - A tenant" | I13: =_xlfn.CONCAT("rename ",A13," ",E13) -> rename q23_1_1 tenant
A14: q23_1_2 | B14: 13 | C14: Q23_1. Are you currently or previously have been in the past two years...? - A landlord | E14: landlord | H14: =_xlfn.CONCAT("label var ",A14," ",$H$1,C14,$H$1) -> label var q23_1_2 "Q23_1. Are you currently or previously have been in the past two years...? - A landlord" | I14: =_xlfn.CONCAT("rename ",A14," ",E14) -> rename q23_1_2 landlord
A15: q23_1_3 | B15: 14 | C15: Q23_1. Are you currently or previously have been in the past two years...? - A home-owner | E15: home_owner | H15: =_xlfn.CONCAT("label var ",A15," ",$H$1,C15,$H$1) -> label var q23_1_3 "Q23_1. Are you currently or previously have been in the past two years...? - A home-owner" | I15: =_xlfn.CONCAT("rename ",A15," ",E15) -> rename q23_1_3 home_owner
A16: q23_2_01_1 | B16: 15 | C16: Q23_2_1_1. Issues experienced - Including issues with buying or selling property and disputes over title or ownership boundary locations and rights of way and Land Registry matters | D16: AJP | E16: AJP_A1 | H16: =_xlfn.CONCAT("label var ",A16," ",$H$1,C16,$H$1) -> label var q23_2_01_1 "Q23_2_1_1. Issues experienced - Including issues with buying or selling property and disputes over title or ownership boundary locations and rights of way and Land Registry matters"
A17: q23_2_02_1 | B17: 16 | C17: Q23_2_2_1. Issues experienced - Disputes about maintenance including of boundaries trees gardens | D17: AJP | E17: AJP_B1 | H17: =_xlfn.CONCAT("label var ",A17," ",$H$1,C17,$H$1) -> label var q23_2_02_1 "Q23_2_2_1. Issues experienced - Disputes about maintenance including of boundaries trees gardens"
A18: q23_2_02_2 | B18: 17 | C18: Q23_2_2_2. Issues experienced - Problems or disputes to do with noise animals or unpleasant behaviour | D18: AJP | E18: AJP_B2 | H18: =_xlfn.CONCAT("label var ",A18," ",$H$1,C18,$H$1) -> label var q23_2_02_2 "Q23_2_2_2. Issues experienced - Problems or disputes to do with noise animals or unpleasant behaviour"
A19: q23_2_02_3 | B19: 18 | C19: Q23_2_2_3. Issues experienced - Other disputes with neighbours such as issues with parking | D19: AJP | E19: AJP_B3 | H19: =_xlfn.CONCAT("label var ",A19," ",$H$1,C19,$H$1) -> label var q23_2_02_3 "Q23_2_2_3. Issues experienced - Other disputes with neighbours such as issues with parking"
A20: q23_2_03_1 | B20: 19 | C20: Q23_2_3_1. Issues experienced - Problems or disputes with your landlord over your rent or return of deposit | D20: AJP | E20: AJP_C1 | H20: =_xlfn.CONCAT("label var ",A20," ",$H$1,C20,$H$1) -> label var q23_2_03_1 "Q23_2_3_1. Issues experienced - Problems or disputes with your landlord over your rent or return of deposit"
A21: q23_2_03_2 | B21: 20 | C21: Q23_2_3_2. Issues experienced - Problem with your landlord about the condition of your accommodation including damage/repairs | D21: AJP | E21: AJP_C2 | H21: =_xlfn.CONCAT("label var ",A21," ",$H$1,C21,$H$1) -> label var q23_2_03_2 "Q23_2_3_2. Issues experienced - Problem with your landlord about the condition of your accommodation including damage/repairs"
A22: q23_2_03_3 | B22: 21 | C22: Q23_2_3_3. Issues experienced - Eviction or threats of eviction or other harassment by a landlord | D22: AJP | E22: AJP_C3 | H22: =_xlfn.CONCAT("label var ",A22," ",$H$1,C22,$H$1) -> label var q23_2_03_3 "Q23_2_3_3. Issues experienced - Eviction or threats of eviction or other harassment by a landlord"
A23: q23_2_04_1 | B23: 22 | C23: Q23_2_4_1. Issues experienced - Issues with a tenant such as delayed/no payment of rent or dispute over a deposit | D23: AJP | E23: AJP_D1 | H23: =_xlfn.CONCAT("label var ",A23," ",$H$1,C23,$H$1) -> label var q23_2_04_1 "Q23_2_4_1. Issues experienced - Issues with a tenant such as delayed/no payment of rent or dispute over a deposit"
A24: q23_2_04_2 | B24: 23 | C24: Q23_2_4_2. Issues experienced - Property-related issues such as damage by tenants or access to property | D24: AJP | E24: AJP_D2 | H24: =_xlfn.CONCAT("label var ",A24," ",$H$1,C24,$H$1) -> label var q23_2_04_2 "Q23_2_4_2. Issues experienced - Property-related issues such as damage by tenants or access to property"
A25: q23_2_04_3 | B25: 24 | C25: Q23_2_4_3. Issues experienced - Issues with tenants such as evictions or complaints | D25: AJP | E25: AJP_D3 | H25: =_xlfn.CONCAT("label var ",A25," ",$H$1,C25,$H$1) -> label var q23_2_04_3 "Q23_2_4_3. Issues experienced - Issues with tenants such as evictions or complaints"
A26: q23_2_05_1 | B26: 25 | C26: Q23_2_5_1. Issues experienced - Building/planning related disputes | D26: AJP | E26: AJP_E1 | H26: =_xlfn.CONCAT("label var ",A26," ",$H$1,C26,$H$1) -> label var q23_2_05_1 "Q23_2_5_1. Issues experienced - Building/planning related disputes"
A27: q23_2_05_2 | B27: 26 | C27: Q23_2_5_2. Issues experienced - Issues with builders/tradespeople about the quality of construction or repairs or disputes about costs | D27: AJP | E27: AJP_E2 | H27: =_xlfn.CONCAT("label var ",A27," ",$H$1,C27,$H$1) -> label var q23_2_05_2 "Q23_2_5_2. Issues experienced - Issues with builders/tradespeople about the quality of construction or repairs or disputes about costs"
... A71: q23_2_14_4 | B71: 70 | C71: Q23_2_14_4. Issues experienced - Other employment-related disputes | D71: AJP | E71: AJP_N4 | H71: =_xlfn.CONCAT("label var ",A71," ",$H$1,C71,$H$1) -> label var q23_2_14_4 "Q23_2_14_4. Issues experienced - Other employment-related disputes"
A72: q23_3_01_1 | B72: 71 | C72: Q23_3_1_1. Frequency experienced - Including issues with buying or selling property and disputes over title or ownership boundary locations and rights of way and Land Registry matters | E72: AJP_A1_freq | H72: =_xlfn.CONCAT("label var ",A72," ",$H$1,C72,$H$1) -> label var q23_3_01_1 "Q23_3_1_1. Frequency experienced - Including issues with buying or selling property and disputes over title or ownership boundary locations and rights of way and Land Registry matters"
A73: q23_3_02_1 | B73: 72 | C73: Q23_3_2_1. Frequency experienced - Disputes about maintenance including of boundaries trees gardens | E73: AJP_B1_freq | H73: =_xlfn.CONCAT("label var ",A73," ",$H$1,C73,$H$1) -> label var q23_3_02_1 "Q23_3_2_1. Frequency experienced - Disputes about maintenance including of boundaries trees gardens"
A74: q23_3_02_2 | B74: 73 | C74: Q23_3_2_2. Frequency experienced - Problems or disputes to do with noise animals or unpleasant behaviour | E74: AJP_B2_freq | H74: =_xlfn.CONCAT("label var ",A74," ",$H$1,C74,$H$1) -> label var q23_3_02_2 "Q23_3_2_2. Frequency experienced - Problems or disputes to do with noise animals or unpleasant behaviour"
A75: q23_3_02_3 | B75: 74 | C75: Q23_3_2_3. Frequency experienced - Other disputes with neighbours such as issues with parking | E75: AJP_B3_freq | H75: =_xlfn.CONCAT("label var ",A75," ",$H$1,C75,$H$1) -> label var q23_3_02_3 "Q23_3_2_3. Frequency experienced - Other disputes with neighbours such as issues with parking"
A76: q23_3_03_1 | B76: 75 | C76: Q23_3_3_1. Frequency experienced - Problems or disputes with your landlord over your rent or return of deposit | E76: AJP_C1_freq | H76: =_xlfn.CONCAT("label var ",A76," ",$H$1,C76,$H$1) -> label var q23_3_03_1 "Q23_3_3_1. Frequency experienced - Problems or disputes with your landlord over your rent or return of deposit"
A77: q23_3_03_2 | B77: 76 | C77: Q23_3_3_2. Frequency experienced - Problem with your landlord about the condition of your accommodation including damage/repairs | E77: AJP_C2_freq | H77: =_xlfn.CONCAT("label var ",A77," ",$H$1,C77,$H$1) -> label var q23_3_03_2 "Q23_3_3_2. Frequency experienced - Problem with your landlord about the condition of your accommodation including damage/repairs"
A78: q23_3_03_3 | B78: 77 | C78: Q23_3_3_3. Frequency experienced - Eviction or threats of eviction or other harassment by a landlord | E78: AJP_C3_freq | H78: =_xlfn.CONCAT("label var ",A78," ",$H$1,C78,$H$1) -> label var q23_3_03_3 "Q23_3_3_3. Frequency experienced - Eviction or threats of eviction or other harassment by a landlord"
A79: q23_3_04_1 | B79: 78 | C79: Q23_3_4_1. Frequency experienced - Issues with a tenant such as delayed/no payment of rent or dispute over a deposit | E79: AJP_D1_freq | H79: =_xlfn.CONCAT("label var ",A79," ",$H$1,C79,$H$1) -> label var q23_3_04_1 "Q23_3_4_1. Frequency experienced - Issues with a tenant such as delayed/no payment of rent or dispute over a deposit"
A80: q23_3_04_2 | B80: 79 | C80: Q23_3_4_2. Frequency experienced - Property-related issues such as damage by tenants or access to property | E80: AJP_D2_freq | H80: =_xlfn.CONCAT("label var ",A80," ",$H$1,C80,$H$1) -> label var q23_3_04_2 "Q23_3_4_2. Frequency experienced - Property-related issues such as damage by tenants or access to property"
A81: q23_3_04_3 | B81: 80 | C81: Q23_3_4_3. Frequency experienced - Issues with tenants such as evictions or complaints | E81: AJP_D3_freq | H81: =_xlfn.CONCAT("label var ",A81," ",$H$1,C81,$H$1) -> label var q23_3_04_3 "Q23_3_4_3. Frequency experienced - Issues with tenants such as evictions or complaints"
A82: q23_3_05_1 | B82: 81 | C82: Q23_3_5_1. Frequency experienced - Building/planning related disputes | E82: AJP_E1_freq | H82: =_xlfn.CONCAT("label var ",A82," ",$H$1,C82,$H$1) -> label var q23_3_05_1 "Q23_3_5_1. Frequency experienced - Building/planning related disputes"
A83: q23_3_05_2 | B83: 82 | C83: Q23_3_5_2. Frequency experienced - Issues with builders/tradespeople about the quality of construction or repairs or disputes about costs | E83: AJP_E2_freq | H83: =_xlfn.CONCAT("label var ",A83," ",$H$1,C83,$H$1) -> label var q23_3_05_2 "Q23_3_5_2. Frequency experienced - Issues with builders/tradespeople about the quality of construction or repairs or disputes about costs"
... A127: q23_3_14_4 | B127: 126 | C127: Q23_3_14_4. Frequency experienced - Other employment-related disputes | E127: AJP_N4_freq | H127: =_xlfn.CONCAT("label var ",A127," ",$H$1,C127,$H$1) -> label var q23_3_14_4 "Q23_3_14_4. Frequency experienced - Other employment-related disputes"
A128: q23_2_catselected | B128: 127 | C128: Q23_2. Categorization Selected | E128: AJP_cat_selected | G128: Parent category of problems selected | H128: =_xlfn.CONCAT("label var ",A128," ",$H$1,C128,$H$1) -> label var q23_2_catselected "Q23_2. Categorization Selected"
A129: q23_4_01_1 | B129: 128 | C129: Q23_4_1_1. Issue ranking - Including issues with buying or selling property and disputes over title or ownership boundary locations and rights of way and Land Registry matters | E129: AJP_A1_rank | H129: =_xlfn.CONCAT("label var ",A129," ",$H$1,C129,$H$1) -> label var q23_4_01_1 "Q23_4_1_1. Issue ranking - Including issues with buying or selling property and disputes over title or ownership boundary locations and rights of way and Land Registry matters"
A130: q23_4_02_1 | B130: 129 | C130: Q23_4_2_1. Issue ranking - Disputes about maintenance including of boundaries trees gardens | E130: AJP_B1_rank | H130: =_xlfn.CONCAT("label var ",A130," ",$H$1,C130,$H$1) -> label var q23_4_02_1 "Q23_4_2_1. Issue ranking - Disputes about maintenance including of boundaries trees gardens"
A131: q23_4_02_2 | B131: 130 | C131: Q23_4_2_2. Issue ranking - Problems or disputes to do with noise animals or unpleasant behaviour | E131: AJP_B2_rank | H131: =_xlfn.CONCAT("label var ",A131," ",$H$1,C131,$H$1) -> label var q23_4_02_2 "Q23_4_2_2. Issue ranking - Problems or disputes to do with noise animals or unpleasant behaviour"
A132: q23_4_02_3 | B132: 131 | C132: Q23_4_2_3. Issue ranking - Other disputes with neighbours such as issues with parking | E132: AJP_B3_rank | H132: =_xlfn.CONCAT("label var ",A132," ",$H$1,C132,$H$1) -> label var q23_4_02_3 "Q23_4_2_3. Issue ranking - Other disputes with neighbours such as issues with parking"
A133: q23_4_03_1 | B133: 132 | C133: Q23_4_3_1. Issue ranking - Problems or disputes with your landlord over your rent or return of deposit | E133: AJP_C1_rank | H133: =_xlfn.CONCAT("label var ",A133," ",$H$1,C133,$H$1) -> label var q23_4_03_1 "Q23_4_3_1. Issue ranking - Problems or disputes with your landlord over your rent or return of deposit"
A134: q23_4_03_2 | B134: 133 | C134: Q23_4_3_2. Issue ranking - Problem with your landlord about the condition of your accommodation including damage/repairs | E134: AJP_C2_rank | H134: =_xlfn.CONCAT("label var ",A134," ",$H$1,C134,$H$1) -> label var q23_4_03_2 "Q23_4_3_2. Issue ranking - Problem with your landlord about the condition of your accommodation including damage/repairs"
A135: q23_4_03_3 | B135: 134 | C135: Q23_4_3_3. Issue ranking - Eviction or threats of eviction or other harassment by a landlord | E135: AJP_C3_rank | H135: =_xlfn.CONCAT("label var ",A135," ",$H$1,C135,$H$1) -> label var q23_4_03_3 "Q23_4_3_3. Issue ranking - Eviction or threats of eviction or other harassment by a landlord"
A136: q23_4_04_1 | B136: 135 | C136: Q23_4_4_1. Issue ranking - Issues with a tenant such as delayed/no payment of rent or dispute over a deposit | E136: AJP_D1_rank | H136: =_xlfn.CONCAT("label var ",A136," ",$H$1,C136,$H$1) -> label var q23_4_04_1 "Q23_4_4_1. Issue ranking - Issues with a tenant such as delayed/no payment of rent or dispute over a deposit"
A137: q23_4_04_2 | B137: 136 | C137: Q23_4_4_2. Issue ranking - Property-related issues such as damage by tenants or access to property | E137: AJP_D2_rank | H137: =_xlfn.CONCAT("label var ",A137," ",$H$1,C137,$H$1) -> label var q23_4_04_2 "Q23_4_4_2. Issue ranking - Property-related issues such as damage by tenants or access to property"
A138: q23_4_04_3 | B138: 137 | C138: Q23_4_4_3. Issue ranking - Issues with tenants such as evictions or complaints | E138: AJP_D3_rank | H138: =_xlfn.CONCAT("label var ",A138," ",$H$1,C138,$H$1) -> label var q23_4_04_3 "Q23_4_4_3. Issue ranking - Issues with tenants such as evictions or complaints"
A139: q23_4_05_1 | B139: 138 | C139: Q23_4_5_1. Issue ranking - Building/planning related disputes | E139: AJP_E1_rank | H139: =_xlfn.CONCAT("label var ",A139," ",$H$1,C139,$H$1) -> label var q23_4_05_1 "Q23_4_5_1. Issue ranking - Building/planning related disputes"
A140: q23_4_05_2 | B140: 139 | C140: Q23_4_5_2. Issue ranking - Issues with builders/tradespeople about the quality of construction or repairs or disputes about costs | E140: AJP_E2_rank | H140: =_xlfn.CONCAT("label var ",A140," ",$H$1,C140,$H$1) -> label var q23_4_05_2 "Q23_4_5_2. Issue ranking - Issues with builders/tradespeople about the quality of construction or repairs or disputes about costs"
... A184: q23_4_14_4 | B184: 183 | C184: Q23_4_14_4. Issue ranking - Other employment-related disputes | E184: AJP_N4_rank | H184: =_xlfn.CONCAT("label var ",A184," ",$H$1,C184,$H$1) -> label var q23_4_14_4 "Q23_4_14_4. Issue ranking - Other employment-related disputes"
A185: q23_4_recentissue_selected | B185: 184 | C185: Q23_4. Recent Issue Selected | D185: AJP_problem | E185: AJP_problem | H185: =_xlfn.CONCAT("label var ",A185," ",$H$1,C185,$H$1) -> label var q23_4_recentissue_selected "Q23_4. Recent Issue Selected"
A186: q24 | B186: 185 | C186: Q24. Is this issue still ongoing or is it done with, either because it is resolved or because you, and anyone else, have given up trying to resolve it? | D186: AJR_state_noresol/AJR_state_resol | E186: AJR_status | H186: =_xlfn.CONCAT("label var ",A186," ",$H$1,C186,$H$1) -> label var q24 "Q24. Is this issue still ongoing or is it done with, either because it is resolved or because you, and anyone else, have given up trying to resolve it?"
A187: q24_1_1 | B187: 186 | C187: Q24_1. Which of the following describes the current status of the issue? - A formal legal process is ongoing (e.g. at a court or tribunal) | E187: AJR_status_cur_1 | H187: =_xlfn.CONCAT("label var ",A187," ",$H$1,C187,$H$1) -> label var q24_1_1 "Q24_1. Which of the following describes the current status of the issue? - A formal legal process is ongoing (e.g. at a court or tribunal)"
A188: q24_1_2 | B188: 187 | C188: Q24_1. Which of the following describes the current status of the issue? - Another dispute resolution process outside a court or a tribunal is ongoing | E188: AJR_status_cur_2 | H188: =_xlfn.CONCAT("label var ",A188," ",$H$1,C188,$H$1) -> label var q24_1_2 "Q24_1. Which of the following describes the current status of the issue? - Another dispute resolution process outside a court or a tribunal is ongoing"
A189: q24_1_3 | B189: 188 | C189: Q24_1. Which of the following describes the current status of the issue? - There is no dispute resolution process ongoing, but I am actively seeking advice or support to resolve or finish it | E189: AJR_status_cur_3 | H189: =_xlfn.CONCAT("label var ",A189," ",$H$1,C189,$H$1) -> label var q24_1_3 "Q24_1. Which of the following describes the current status of the issue? - There is no dispute resolution process ongoing, but I am actively seeking advice or support to resolve or finish it"
A190: q24_1_4 | B190: 189 | C190: Q24_1. Which of the following describes the current status of the issue? - I have not taken recent action as I am waiting for the other party to act or respond | E190: AJR_status_cur_4 | H190: =_xlfn.CONCAT("label var ",A190," ",$H$1,C190,$H$1) -> label var q24_1_4 "Q24_1. Which of the following describes the current status of the issue? - I have not taken recent action as I am waiting for the other party to act or respond"
A191: q24_1_5 | B191: 190 | C191: Q24_1. Which of the following describes the current status of the issue? - No recent action has been taken, but I still intend to resolve it | E191: AJR_status_cur_5 | H191: =_xlfn.CONCAT("label var ",A191," ",$H$1,C191,$H$1) -> label var q24_1_5 "Q24_1. Which of the following describes the current status of the issue? - No recent action has been taken, but I still intend to resolve it"
A192: q24_1_6 | B192: 191 | C192: Q24_1. Which of the following describes the current status of the issue? - No recent action has been taken | E192: AJR_status_cur_6 | H192: =_xlfn.CONCAT("label var ",A192," ",$H$1,C192,$H$1) -> label var q24_1_6 "Q24_1. Which of the following describes the current status of the issue? - No recent action has been taken"
A193: q24_1_7 | B193: 192 | C193: Q24_1. Which of the following describes the current status of the issue? - Other, please specify: | E193: AJR_status_cur_7 | H193: =_xlfn.CONCAT("label var ",A193," ",$H$1,C193,$H$1) -> label var q24_1_7 "Q24_1. Which of the following describes the current status of the issue? - Other, please specify:"
A194: q24_1_8 | B194: 193 | C194: Q24_1. Which of the following describes the current status of the issue? - Don't know | E194: AJR_status_cur_8 | H194: =_xlfn.CONCAT("label var ",A194," ",$H$1,C194,$H$1) -> label var q24_1_8 "Q24_1. Which of the following describes the current status of the issue? - Don't know"
A195: q24_1_9 | B195: 194 | C195: Q24_1. Which of the following describes the current status of the issue? - Prefer not to say | E195: AJR_status_cur_9 | H195: =_xlfn.CONCAT("label var ",A195," ",$H$1,C195,$H$1) -> label var q24_1_9 "Q24_1. Which of the following describes the current status of the issue? - Prefer not to say"
A196: q25_1_01 | B196: 195 | C196: Q25_1. Help sought - A court (small claims court, District Court, High Court, Court of Appeal, Supreme Court, Europe etc) | D196: AJD_inst_advice, AJD_adviser_1-99 | E196: AJD_adviser_1 | H196: =_xlfn.CONCAT("label var ",A196," ",$H$1,C196,$H$1) -> label var q25_1_01 "Q25_1. Help sought - A court (small claims court, District Court, High Court, Court of Appeal, Supreme Court, Europe etc)"
A197: q25_1_02 | B197: 196 | C197: Q25_1. Help sought - A tribunal (e.g. International Protection Appeals Tribunal, Workplace Relations Commission, Social Welfare Appeals Office, | D197: AJD_inst_advice, AJD_adviser_1-99 | E197: AJD_adviser_2 | H197: =_xlfn.CONCAT("label var ",A197," ",$H$1,C197,$H$1) -> label var q25_1_02 "Q25_1. Help sought - A tribunal (e.g. International Protection Appeals Tribunal, Workplace Relations Commission, Social Welfare Appeals Office,"
A198: q25_1_03 | B198: 197 | C198: Q25_1. Help sought - An Ombudsman (e.g. Financial Services Ombudsman) | D198: AJD_inst_advice, AJD_adviser_1-99 | E198: AJD_adviser_3 | H198: =_xlfn.CONCAT("label var ",A198," ",$H$1,C198,$H$1) -> label var q25_1_03 "Q25_1. Help sought - An Ombudsman (e.g. Financial Services Ombudsman)"
A199: q25_1_04 | B199: 198 | C199: Q25_1. Help sought - The Gardai/police (or other law-enforcement) | D199: AJD_inst_advice, AJD_adviser_1-99 | E199: AJD_adviser_4 | H199: =_xlfn.CONCAT("label var ",A199," ",$H$1,C199,$H$1) -> label var q25_1_04 "Q25_1. Help sought - The Gardai/police (or other law-enforcement)"
A200: q25_1_05 | B200: 199 | C200: Q25_1. Help sought - Family Mediation Service | D200: AJD_inst_advice, AJD_adviser_1-99 | E200: AJD_adviser_5 | H200: =_xlfn.CONCAT("label var ",A200," ",$H$1,C200,$H$1) -> label var q25_1_05 "Q25_1. Help sought - Family Mediation Service"
A201: q25_1_06 | B201: 200 | C201: Q25_1. Help sought - Another mediation, conciliation or other complaint or dispute resolution service (including online or commercial services) | D201: AJD_inst_advice, AJD_adviser_1-99 | E201: AJD_adviser_6 | H201: =_xlfn.CONCAT("label var ",A201," ",$H$1,C201,$H$1) -> label var q25_1_06 "Q25_1. Help sought - Another mediation, conciliation or other complaint or dispute resolution service (including online or commercial services)"
A202: q25_1_07 | B202: 201 | C202: Q25_1. Help sought - A private solicitor or person working in a solicitor's office | D202: AJD_inst_advice, AJD_adviser_1-99 | E202: AJD_adviser_7 | H202: =_xlfn.CONCAT("label var ",A202," ",$H$1,C202,$H$1) -> label var q25_1_07 "Q25_1. Help sought - A private solicitor or person working in a solicitor's office"
A203: q25_1_08 | B203: 202 | C203: Q25_1. Help sought - A private barrister or person working in a barrister's office | D203: AJD_inst_advice, AJD_adviser_1-99 | E203: AJD_adviser_8 | H203: =_xlfn.CONCAT("label var ",A203," ",$H$1,C203,$H$1) -> label var q25_1_08 "Q25_1. Help sought - A private barrister or person working in a barrister's office"
A204: q25_1_09 | B204: 203 | C204: Q25_1. Help sought - A Legal Aid Board Law Centre | D204: AJD_inst_advice, AJD_adviser_1-99 | E204: AJD_adviser_9 | H204: =_xlfn.CONCAT("label var ",A204," ",$H$1,C204,$H$1) -> label var q25_1_09 "Q25_1. Help sought - A Legal Aid Board Law Centre"
A205: q25_1_10 | B205: 204 | C205: Q25_1. Help sought - Another law centre such as the Free Legal Advice Centres | D205: AJD_inst_advice, AJD_adviser_1-99 | E205: AJD_adviser_10 | H205: =_xlfn.CONCAT("label var ",A205," ",$H$1,C205,$H$1) -> label var q25_1_10 "Q25_1. Help sought - Another law centre such as the Free Legal Advice Centres"
A206: q25_1_11 | B206: 205 | C206: Q25_1. Help sought - A government department, local council or government agency (e.g. a Housing or Social Welfare officer) | D206: AJD_inst_advice, AJD_adviser_1-99 | E206: AJD_adviser_11 | H206: =_xlfn.CONCAT("label var ",A206," ",$H$1,C206,$H$1) -> label var q25_1_11 "Q25_1. Help sought - A government department, local council or government agency (e.g. a Housing or Social Welfare officer)"
A207: q25_1_12 | B207: 206 | C207: Q25_1. Help sought - A non-legal professional, organisation or help line (e.g. Citizens Information Centre, Citizens Information Phone Centre, | D207: AJD_inst_advice, AJD_adviser_1-99 | E207: AJD_adviser_12 | H207: =_xlfn.CONCAT("label var ",A207," ",$H$1,C207,$H$1) -> label var q25_1_12 "Q25_1. Help sought - A non-legal professional, organisation or help line (e.g. Citizens Information Centre, Citizens Information Phone Centre,"
... A212: q25_1_17 | B212: 211 | C212: Q25_1. Help sought - Another person (e.g. a friend, family member, or acquaintance [not a professional]) | D212: AJD_inst_advice, AJD_adviser_1-99 | E212: AJD_adviser_17 | H212: =_xlfn.CONCAT("label var ",A212," ",$H$1,C212,$H$1) -> label var q25_1_17 "Q25_1. Help sought - Another person (e.g. a friend, family member, or acquaintance [not a professional])"
A213: q25_7_01 | B213: 212 | C213: Q25_7. How helpful were each of the following? - A court | E213: AJD_adviser_help_1 | H213: =_xlfn.CONCAT("label var ",A213," ",$H$1,C213,$H$1) -> label var q25_7_01 "Q25_7. How helpful were each of the following? - A court"
A214: q25_7_02 | B214: 213 | C214: Q25_7. How helpful were each of the following? - A tribunal | E214: AJD_adviser_help_2 | H214: =_xlfn.CONCAT("label var ",A214," ",$H$1,C214,$H$1) -> label var q25_7_02 "Q25_7. How helpful were each of the following? - A tribunal"
A215: q25_7_03 | B215: 214 | C215: Q25_7. How helpful were each of the following? - An Ombudsman | E215: AJD_adviser_help_3 | H215: =_xlfn.CONCAT("label var ",A215," ",$H$1,C215,$H$1) -> label var q25_7_03 "Q25_7. How helpful were each of the following? - An Ombudsman"
A216: q25_7_04 | B216: 215 | C216: Q25_7. How helpful were each of the following? - The Gardai/police | E216: AJD_adviser_help_4 | H216: =_xlfn.CONCAT("label var ",A216," ",$H$1,C216,$H$1) -> label var q25_7_04 "Q25_7. How helpful were each of the following? - The Gardai/police"
A217: q25_7_05 | B217: 216 | C217: Q25_7. How helpful were each of the following? - Family Mediation Service | E217: AJD_adviser_help_5 | H217: =_xlfn.CONCAT("label var ",A217," ",$H$1,C217,$H$1) -> label var q25_7_05 "Q25_7. How helpful were each of the following? - Family Mediation Service"
A218: q25_7_06 | B218: 217 | C218: Q25_7. How helpful were each of the following? - Another mediation, conciliation or other complaint or dispute resolution service | E218: AJD_adviser_help_6 | H218: =_xlfn.CONCAT("label var ",A218," ",$H$1,C218,$H$1) -> label var q25_7_06 "Q25_7. How helpful were each of the following? - Another mediation, conciliation or other complaint or dispute resolution service"
A219: q25_7_07 | B219: 218 | C219: Q25_7. How helpful were each of the following? - A private solicitor or person working in a solicitor's office | E219: AJD_adviser_help_7 | H219: =_xlfn.CONCAT("label var ",A219," ",$H$1,C219,$H$1) -> label var q25_7_07 "Q25_7. How helpful were each of the following? - A private solicitor or person working in a solicitor's office"
A220: q25_7_08 | B220: 219 | C220: Q25_7. How helpful were each of the following? - A private barrister or person working in a barrister's office | E220: AJD_adviser_help_8 | H220: =_xlfn.CONCAT("label var ",A220," ",$H$1,C220,$H$1) -> label var q25_7_08 "Q25_7. How helpful were each of the following? - A private barrister or person working in a barrister's office"
A221: q25_7_09 | B221: 220 | C221: Q25_7. How helpful were each of the following? - A Legal Aid Board Law Centre | E221: AJD_adviser_help_9 | H221: =_xlfn.CONCAT("label var ",A221," ",$H$1,C221,$H$1) -> label var q25_7_09 "Q25_7. How helpful were each of the following? - A Legal Aid Board Law Centre"
A222: q25_7_10 | B222: 221 | C222: Q25_7. How helpful were each of the following? - Another law centre such as the Free Legal Advice Centres | E222: AJD_adviser_help_10 | H222: =_xlfn.CONCAT("label var ",A222," ",$H$1,C222,$H$1) -> label var q25_7_10 "Q25_7. How helpful were each of the following? - Another law centre such as the Free Legal Advice Centres"
A223: q25_7_11 | B223: 222 | C223: Q25_7. How helpful were each of the following? - A government department, local council or government agency | E223: AJD_adviser_help_11 | H223: =_xlfn.CONCAT("label var ",A223," ",$H$1,C223,$H$1) -> label var q25_7_11 "Q25_7. How helpful were each of the following? - A government department, local council or government agency"
A224: q25_7_12 | B224: 223 | C224: Q25_7. How helpful were each of the following? - A non-legal professional, organisation or help line | E224: AJD_adviser_help_12 | H224: =_xlfn.CONCAT("label var ",A224," ",$H$1,C224,$H$1) -> label var q25_7_12 "Q25_7. How helpful were each of the following? - A non-legal professional, organisation or help line"
... A249: q25_5 | B249: 248 | C249: Q25_5. Just to check, have you done / did you do anything, or do you expect to do anything to resolve or end this issue, such as talking to the other party? | E249: AJR_action | H249: =_xlfn.CONCAT("label var ",A249," ",$H$1,C249,$H$1) -> label var q25_5 "Q25_5. Just to check, have you done / did you do anything, or do you expect to do anything to resolve or end this issue, such as talking to the other party?"
A250: q25_6_01 | B250: 249 | C250: Q25_6. For which of the following reasons, if any, haven't you done / didn't you do anything to try to resolve the issue? - It wasn't very important | D250: AJD_noadvice_reason | E250: AJR_noaction_1 | H250: =_xlfn.CONCAT("label var ",A250," ",$H$1,C250,$H$1) -> label var q25_6_01 "Q25_6. For which of the following reasons, if any, haven't you done / didn't you do anything to try to resolve the issue? - It wasn't very important"
A251: q25_6_02 | B251: 250 | C251: Q25_6. For which of the following reasons, if any, haven't you done / didn't you do anything to try to resolve the issue? - It was resolved quickly | D251: AJD_noadvice_reason | E251: AJR_noaction_2 | H251: =_xlfn.CONCAT("label var ",A251," ",$H$1,C251,$H$1) -> label var q25_6_02 "Q25_6. For which of the following reasons, if any, haven't you done / didn't you do anything to try to resolve the issue? - It was resolved quickly"
A252: q25_6_03 | B252: 251 | C252: Q25_6. For which of the following reasons, if any, haven't you done / didn't you do anything to try to resolve the issue? - It would take too long | D252: AJD_noadvice_reason | E252: AJR_noaction_3 | H252: =_xlfn.CONCAT("label var ",A252," ",$H$1,C252,$H$1) -> label var q25_6_03 "Q25_6. For which of the following reasons, if any, haven't you done / didn't you do anything to try to resolve the issue? - It would take too long"
A253: q25_6_04 | B253: 252 | C253: Q25_6. For which of the following reasons, if any, haven't you done / didn't you do anything to try to resolve the issue? - It would be too stressful | D253: AJD_noadvice_reason | E253: AJR_noaction_4 | H253: =_xlfn.CONCAT("label var ",A253," ",$H$1,C253,$H$1) -> label var q25_6_04 "Q25_6. For which of the following reasons, if any, haven't you done / didn't you do anything to try to resolve the issue? - It would be too stressful"
A254: q25_6_05 | B254: 253 | C254: Q25_6. For which of the following reasons, if any, haven't you done / didn't you do anything to try to resolve the issue? - It would cost too much | D254: AJD_noadvice_reason | E254: AJR_noaction_5 | H254: =_xlfn.CONCAT("label var ",A254," ",$H$1,C254,$H$1) -> label var q25_6_05 "Q25_6. For which of the following reasons, if any, haven't you done / didn't you do anything to try to resolve the issue? - It would cost too much"
A255: q25_6_06 | B255: 254 | C255: Q25_6. For which of the following reasons, if any, haven't you done / didn't you do anything to try to resolve the issue? - It would damage the relationship with the other side | D255: AJD_noadvice_reason | E255: AJR_noaction_6 | H255: =_xlfn.CONCAT("label var ",A255," ",$H$1,C255,$H$1) -> label var q25_6_06 "Q25_6. For which of the following reasons, if any, haven't you done / didn't you do anything to try to resolve the issue? - It would damage the relationship with the other side"
A256: q25_6_07 | B256: 255 | C256: Q25_6. For which of the following reasons, if any, haven't you done / didn't you do anything to try to resolve the issue? - It would make you uncomfortable/ you were too ashamed or embarrassed to ask for help | D256: AJD_noadvice_reason | E256: AJR_noaction_7 | H256: =_xlfn.CONCAT("label var ",A256," ",$H$1,C256,$H$1) -> label var q25_6_07 "Q25_6. For which of the following reasons, if any, haven't you done / didn't you do anything to try to resolve the issue? - It would make you uncomfortable/ you were too ashamed or embarrassed to ask for help"
A257: q25_6_08 | B257: 256 | C257: Q25_6. For which of the following reasons, if any, haven't you done / didn't you do anything to try to resolve the issue? - It would make no difference | D257: AJD_noadvice_reason | E257: AJR_noaction_8 | H257: =_xlfn.CONCAT("label var ",A257," ",$H$1,C257,$H$1) -> label var q25_6_08 "Q25_6. For which of the following reasons, if any, haven't you done / didn't you do anything to try to resolve the issue? - It would make no difference"
...

Sheet Variable Values
A1: WJP label | B1: Question label | C1: Value | E1: Label
A2: =VLOOKUP($C2,'Variable Information'!$A$2:$E$480,5,FALSE) -> gend | B2: =VLOOKUP($C2,'Variable Information'!$A$1:$C$480,3,FALSE) -> Q11. Gender. Do you identify as: | C2: q11 | D2: 1 | E2: Male
A3: =VLOOKUP($C3,'Variable Information'!$A$2:$E$480,5,FALSE) -> #N/A | B3: =VLOOKUP($C3,'Variable Information'!$A$1:$C$480,3,FALSE) -> #N/A | D3: 2 | E3: Female
A4: =VLOOKUP($C4,'Variable Information'!$A$2:$E$480,5,FALSE) -> #N/A | B4: =VLOOKUP($C4,'Variable Information'!$A$1:$C$480,3,FALSE) -> #N/A | D4: 3 | E4: Other/Prefer not to say
A5: =VLOOKUP($C5,'Variable Information'!$A$2:$E$480,5,FALSE) -> age | B5: =VLOOKUP($C5,'Variable Information'!$A$1:$C$480,3,FALSE) -> Q3. Age | C5: q03 | D5: 1 | E5: 18-24
A6: =VLOOKUP($C6,'Variable Information'!$A$2:$E$480,5,FALSE) -> #N/A | B6: =VLOOKUP($C6,'Variable Information'!$A$1:$C$480,3,FALSE) -> #N/A | D6: 2 | E6: 25-34
A7: =VLOOKUP($C7,'Variable Information'!$A$2:$E$480,5,FALSE) -> #N/A | B7: =VLOOKUP($C7,'Variable Information'!$A$1:$C$480,3,FALSE) -> #N/A | D7: 3 | E7: 35-44
A8: =VLOOKUP($C8,'Variable Information'!$A$2:$E$480,5,FALSE) -> #N/A | B8: =VLOOKUP($C8,'Variable Information'!$A$1:$C$480,3,FALSE) -> #N/A | D8: 4 | E8: 45-54
A9: =VLOOKUP($C9,'Variable Information'!$A$2:$E$480,5,FALSE) -> #N/A | B9: =VLOOKUP($C9,'Variable Information'!$A$1:$C$480,3,FALSE) -> #N/A | D9: 5 | E9: 55-64
A10: =VLOOKUP($C10,'Variable Information'!$A$2:$E$480,5,FALSE) -> #N/A | B10: =VLOOKUP($C10,'Variable Information'!$A$1:$C$480,3,FALSE) -> #N/A | D10: 6 | E10: 65-74
A11: =VLOOKUP($C11,'Variable Information'!$A$2:$E$480,5,FALSE) -> #N/A | B11: =VLOOKUP($C11,'Variable Information'!$A$1:$C$480,3,FALSE) -> #N/A | D11: 7 | E11: 75+
A12: =VLOOKUP($C12,'Variable Information'!$A$2:$E$480,5,FALSE) -> edu | B12: =VLOOKUP($C12,'Variable Information'!$A$1:$C$480,3,FALSE) -> Q18. Which of the following is the highest level of education or training you have completed? | C12: q18 | D12: 1 | E12: No formal education/training
A13: =VLOOKUP($C13,'Variable Information'!$A$2:$E$480,5,FALSE) -> #N/A | B13: =VLOOKUP($C13,'Variable Information'!$A$1:$C$480,3,FALSE) -> #N/A | D13: 2 | E13: Primary education
A14: =VLOOKUP($C14,'Variable Information'!$A$2:$E$480,5,FALSE) -> #N/A | B14: =VLOOKUP($C14,'Variable Information'!$A$1:$C$480,3,FALSE) -> #N/A | D14: 3 | E14: Lower secondary - Junior/Inter/Group Certificate
A15: =VLOOKUP($C15,'Variable Information'!$A$2:$E$480,5,FALSE) -> #N/A | B15: =VLOOKUP($C15,'Variable Information'!$A$1:$C$480,3,FALSE) -> #N/A | D15: 4 | E15: Upper Secondary - Leaving Certificate
A16: =VLOOKUP($C16,'Variable Information'!$A$2:$E$480,5,FALSE) -> #N/A | B16: =VLOOKUP($C16,'Variable Information'!$A$1:$C$480,3,FALSE) -> #N/A | D16: 5 | E16: Technical or Vocational
A17: =VLOOKUP($C17,'Variable Information'!$A$2:$E$480,5,FALSE) -> #N/A | B17: =VLOOKUP($C17,'Variable Information'!$A$1:$C$480,3,FALSE) -> #N/A | D17: 6 | E17: Advanced Certificate/Completed Apprenticeship
A18: =VLOOKUP($C18,'Variable Information'!$A$2:$E$480,5,FALSE) -> #N/A | B18: =VLOOKUP($C18,'Variable Information'!$A$1:$C$480,3,FALSE) -> #N/A | D18: 7 | E18: Higher Certificate
A19: =VLOOKUP($C19,'Variable Information'!$A$2:$E$480,5,FALSE) -> #N/A | B19: =VLOOKUP($C19,'Variable Information'!$A$1:$C$480,3,FALSE) -> #N/A | D19: 8 | E19: Ordinary Bachelor's degree or National Diploma
A20: =VLOOKUP($C20,'Variable Information'!$A$2:$E$480,5,FALSE) -> #N/A | B20: =VLOOKUP($C20,'Variable Information'!$A$1:$C$480,3,FALSE) -> #N/A | D20: 9 | E20: Honours Bachelor's degree/Professional Qualification or both
A21: =VLOOKUP($C21,'Variable Information'!$A$2:$E$480,5,FALSE) -> #N/A | B21: =VLOOKUP($C21,'Variable Information'!$A$1:$C$480,3,FALSE) -> #N/A | D21: 10 | E21: Postgraduate Diploma or Master's Degree
A22: =VLOOKUP($C22,'Variable Information'!$A$2:$E$480,5,FALSE) -> #N/A | B22: =VLOOKUP($C22,'Variable Information'!$A$1:$C$480,3,FALSE) -> #N/A | D22: 11 | E22: Doctorate (PhD) or higher
A23: =VLOOKUP($C23,'Variable Information'!$A$2:$E$480,5,FALSE) -> edu_2 | B23: =VLOOKUP($C23,'Variable Information'!$A$1:$C$480,3,FALSE) -> Education | C23: education | D23: 1 | E23: Lower education
A24: =VLOOKUP($C24,'Variable Information'!$A$2:$E$480,5,FALSE) -> #N/A | B24: =VLOOKUP($C24,'Variable Information'!$A$1:$C$480,3,FALSE) -> #N/A | D24: 2 | E24: Higher education
A25: =VLOOKUP($C25,'Variable Information'!$A$2:$E$480,5,FALSE) -> emp | B25: =VLOOKUP($C25,'Variable Information'!$A$1:$C$480,3,FALSE) -> Q17. Which one of the following best describes your current situation? | C25: q17 | D25: 1 | E25: Employed
A26: =VLOOKUP($C26,'Variable Information'!$A$2:$E$480,5,FALSE) -> #N/A | B26: =VLOOKUP($C26,'Variable Information'!$A$1:$C$480,3,FALSE) -> #N/A | D26: 2 | E26: Self-employed
A27: =VLOOKUP($C27,'Variable Information'!$A$2:$E$480,5,FALSE) -> #N/A | B27: =VLOOKUP($C27,'Variable Information'!$A$1:$C$480,3,FALSE) -> #N/A | D27: 3 | E27: Unemployed and looking for work
A28: =VLOOKUP($C28,'Variable Information'!$A$2:$E$480,5,FALSE) -> #N/A | B28: =VLOOKUP($C28,'Variable Information'!$A$1:$C$480,3,FALSE) -> #N/A | D28: 4 | E28: Retired
A29: =VLOOKUP($C29,'Variable Information'!$A$2:$E$480,5,FALSE) -> #N/A | B29: =VLOOKUP($C29,'Variable Information'!$A$1:$C$480,3,FALSE) -> #N/A | D29: 5 | E29: Unable to work due to long standing health problems
A30: =VLOOKUP($C30,'Variable Information'!$A$2:$E$480,5,FALSE) -> #N/A | B30: =VLOOKUP($C30,'Variable Information'!$A$1:$C$480,3,FALSE) -> #N/A | D30: 6 | E30: Full time Student/Pupil
A31: =VLOOKUP($C31,'Variable Information'!$A$2:$E$480,5,FALSE) -> #N/A | B31: =VLOOKUP($C31,'Variable Information'!$A$1:$C$480,3,FALSE) -> #N/A | D31: 7 | E31: Looking after home/family
A32: =VLOOKUP($C32,'Variable Information'!$A$2:$E$480,5,FALSE) -> #N/A | B32: =VLOOKUP($C32,'Variable Information'!$A$1:$C$480,3,FALSE) -> #N/A | D32: 8 | E32: Not working and not looking for work
A33: =VLOOKUP($C33,'Variable Information'!$A$2:$E$480,5,FALSE) -> #N/A | B33: =VLOOKUP($C33,'Variable Information'!$A$1:$C$480,3,FALSE) -> #N/A | D33: 9 | E33: Other, please specify:
A34: =VLOOKUP($C34,'Variable Information'!$A$2:$E$480,5,FALSE) -> emp_2 | B34: =VLOOKUP($C34,'Variable Information'!$A$1:$C$480,3,FALSE) -> Employment | C34: employment | D34: 1 | E34: Full-time
A35: =VLOOKUP($C35,'Variable Information'!$A$2:$E$480,5,FALSE) -> #N/A | B35: =VLOOKUP($C35,'Variable Information'!$A$1:$C$480,3,FALSE) -> #N/A | D35: 2 | E35: Others
A36: =VLOOKUP($C36,'Variable Information'!$A$2:$E$480,5,FALSE) -> work | B36: =VLOOKUP($C36,'Variable Information'!$A$1:$C$480,3,FALSE) -> QSocialGrade. Please indicate which occupational group best describes the main earner in your household, or which group fits best. | C36: qsocialgrade | D36: 1 | E36: Higher managerial/ professional/ administrative (e.g. Established doctor, Solicitor, Board Director<br/>in a large organ
A37: =VLOOKUP($C37,'Variable Information'!$A$2:$E$480,5,FALSE) -> #N/A | B37: =VLOOKUP($C37,'Variable Information'!$A$1:$C$480,3,FALSE) -> #N/A | D37: 2 | E37: Intermediate managerial/ professional/ administrative (e.g. Newly qualified (under 3 years) doctor,<br/>Solicitor, Board
A38: =VLOOKUP($C38,'Variable Information'!$A$2:$E$480,5,FALSE) -> #N/A | B38: =VLOOKUP($C38,'Variable Information'!$A$1:$C$480,3,FALSE) -> #N/A | D38: 3 | E38: Supervisory or clerical/ junior managerial/ professional/ administrative (e.g. Office worker,<br/>Student Doctor, Forema
A39: =VLOOKUP($C39,'Variable Information'!$A$2:$E$480,5,FALSE) -> #N/A | B39: =VLOOKUP($C39,'Variable Information'!$A$1:$C$480,3,FALSE) -> #N/A | D39: 4 | E39: Student
A40: =VLOOKUP($C40,'Variable Information'!$A$2:$E$480,5,FALSE) -> #N/A | B40: =VLOOKUP($C40,'Variable Information'!$A$1:$C$480,3,FALSE) -> #N/A | D40: 5 | E40: Skilled manual worker (e.g. Skilled Bricklayer, Carpenter, Plumber, Painter, Bus/ Ambulance Driver,<br/>HGV driver, AA p
A41: =VLOOKUP($C41,'Variable Information'!$A$2:$E$480,5,FALSE) -> #N/A | B41: =VLOOKUP($C41,'Variable Information'!$A$1:$C$480,3,FALSE) -> #N/A | D41: 6 | E41: Semi or unskilled manual worker (e.g. Manual workers, all apprentices to be skilled trades,<br/>Caretaker, Park keeper,
A42: =VLOOKUP($C42,'Variable Information'!$A$2:$E$480,5,FALSE) -> #N/A | B42: =VLOOKUP($C42,'Variable Information'!$A$1:$C$480,3,FALSE) -> #N/A | D42: 7 | E42: Casual worker - not in permanent employment
A43: =VLOOKUP($C43,'Variable Information'!$A$2:$E$480,5,FALSE) -> #N/A | B43: =VLOOKUP($C43,'Variable Information'!$A$1:$C$480,3,FALSE) -> #N/A | D43: 8 | E43: Housewife/ Homemaker
A44: =VLOOKUP($C44,'Variable Information'!$A$2:$E$480,5,FALSE) -> #N/A | B44: =VLOOKUP($C44,'Variable Information'!$A$1:$C$480,3,FALSE) -> #N/A | D44: 9 | E44: Retired and living on state pension
A45: =VLOOKUP($C45,'Variable Information'!$A$2:$E$480,5,FALSE) -> #N/A | B45: =VLOOKUP($C45,'Variable Information'!$A$1:$C$480,3,FALSE) -> #N/A | D45: 10 | E45: Unemployed or not working due to long-term sickness
A46: =VLOOKUP($C46,'Variable Information'!$A$2:$E$480,5,FALSE) -> #N/A | B46: =VLOOKUP($C46,'Variable Information'!$A$1:$C$480,3,FALSE) -> #N/A | D46: 11 | E46: Full-time carer of other household member
A47: =VLOOKUP($C47,'Variable Information'!$A$2:$E$480,5,FALSE) -> #N/A | B47: =VLOOKUP($C47,'Variable Information'!$A$1:$C$480,3,FALSE) -> #N/A | D47: 12 | E47: Farmer / Agricultural worker
A48: =VLOOKUP($C48,'Variable Information'!$A$2:$E$480,5,FALSE) -> work_2 | B48: =VLOOKUP($C48,'Variable Information'!$A$1:$C$480,3,FALSE) -> Social Grade | C48: socialgrade | D48: 1 | E48: A
A49: =VLOOKUP($C49,'Variable Information'!$A$2:$E$480,5,FALSE) -> #N/A | B49: =VLOOKUP($C49,'Variable Information'!$A$1:$C$480,3,FALSE) -> #N/A | D49: 2 | E49: B
A50: =VLOOKUP($C50,'Variable Information'!$A$2:$E$480,5,FALSE) -> #N/A | B50: =VLOOKUP($C50,'Variable Information'!$A$1:$C$480,3,FALSE) -> #N/A | D50: 3 | E50: C1
A51: =VLOOKUP($C51,'Variable Information'!$A$2:$E$480,5,FALSE) -> #N/A | B51: =VLOOKUP($C51,'Variable Information'!$A$1:$C$480,3,FALSE) -> #N/A | D51: 4 | E51: C2
A52: =VLOOKUP($C52,'Variable Information'!$A$2:$E$480,5,FALSE) -> #N/A | B52: =VLOOKUP($C52,'Variable Information'!$A$1:$C$480,3,FALSE) -> #N/A | D52: 5 | E52: D
A53: =VLOOKUP($C53,'Variable Information'!$A$2:$E$480,5,FALSE) -> #N/A | B53: =VLOOKUP($C53,'Variable Information'!$A$1:$C$480,3,FALSE) -> #N/A | D53: 6 | E53: E
A54: =VLOOKUP($C54,'Variable Information'!$A$2:$E$480,5,FALSE) -> #N/A | B54: =VLOOKUP($C54,'Variable Information'!$A$1:$C$480,3,FALSE) -> #N/A | D54: 7 | E54: F
A55: =VLOOKUP($C55,'Variable Information'!$A$2:$E$480,5,FALSE) -> county | B55: =VLOOKUP($C55,'Variable Information'!$A$1:$C$480,3,FALSE) -> County. What is the name of the county where you currently live? | C55: county | D55: 1 | E55: Carlow
A56: =VLOOKUP($C56,'Variable Information'!$A$2:$E$480,5,FALSE) -> #N/A | B56: =VLOOKUP($C56,'Variable Information'!$A$1:$C$480,3,FALSE) -> #N/A | D56: 2 | E56: Cavan
A57: =VLOOKUP($C57,'Variable Information'!$A$2:$E$480,5,FALSE) -> #N/A | B57: =VLOOKUP($C57,'Variable Information'!$A$1:$C$480,3,FALSE) -> #N/A | D57: 3 | E57: Clare
A58: =VLOOKUP($C58,'Variable Information'!$A$2:$E$480,5,FALSE) -> #N/A | B58: =VLOOKUP($C58,'Variable Information'!$A$1:$C$480,3,FALSE) -> #N/A | D58: 4 | E58: Cork
A59: =VLOOKUP($C59,'Variable Information'!$A$2:$E$480,5,FALSE) -> #N/A | B59: =VLOOKUP($C59,'Variable Information'!$A$1:$C$480,3,FALSE) -> #N/A | D59: 5 | E59: Donegal
A60: =VLOOKUP($C60,'Variable Information'!$A$2:$E$480,5,FALSE) -> #N/A | B60: =VLOOKUP($C60,'Variable Information'!$A$1:$C$480,3,FALSE) -> #N/A | D60: 6 | E60: Dublin
A61: =VLOOKUP($C61,'Variable Information'!$A$2:$E$480,5,FALSE) -> #N/A | B61: =VLOOKUP($C61,'Variable Information'!$A$1:$C$480,3,FALSE) -> #N/A | D61: 7 | E61: Galway
A62: =VLOOKUP($C62,'Variable Information'!$A$2:$E$480,5,FALSE) -> #N/A | B62: =VLOOKUP($C62,'Variable Information'!$A$1:$C$480,3,FALSE) -> #N/A | D62: 8 | E62: Kerry
A63: =VLOOKUP($C63,'Variable Information'!$A$2:$E$480,5,FALSE) -> #N/A | B63: =VLOOKUP($C63,'Variable Information'!$A$1:$C$480,3,FALSE) -> #N/A | D63: 9 | E63: Kildare
A64: =VLOOKUP($C64,'Variable Information'!$A$2:$E$480,5,FALSE) -> #N/A | B64: =VLOOKUP($C64,'Variable Information'!$A$1:$C$480,3,FALSE) -> #N/A | D64: 10 | E64: Kilkenny
A65: =VLOOKUP($C65,'Variable Information'!$A$2:$E$480,5,FALSE) -> #N/A | B65: =VLOOKUP($C65,'Variable Information'!$A$1:$C$480,3,FALSE) -> #N/A | D65: 11 | E65: Laois
A66: =VLOOKUP($C66,'Variable Information'!$A$2:$E$480,5,FALSE) -> #N/A | B66: =VLOOKUP($C66,'Variable Information'!$A$1:$C$480,3,FALSE) -> #N/A | D66: 12 | E66: Leitrim
A67: =VLOOKUP($C67,'Variable Information'!$A$2:$E$480,5,FALSE) -> #N/A | B67: =VLOOKUP($C67,'Variable Information'!$A$1:$C$480,3,FALSE) -> #N/A | D67: 13 | E67: Limerick
... A81: =VLOOKUP($C81,'Variable Information'!$A$2:$E$480,5,FALSE) -> #N/A | B81: =VLOOKUP($C81,'Variable Information'!$A$1:$C$480,3,FALSE) -> #N/A | D81: 27 | E81: None of these
A82: =VLOOKUP($C82,'Variable Information'!$A$2:$E$480,5,FALSE) -> region | B82: =VLOOKUP($C82,'Variable Information'!$A$1:$C$480,3,FALSE) -> Region. | C82: region | D82: 1 | E82: Dublin
A83: =VLOOKUP($C83,'Variable Information'!$A$2:$E$480,5,FALSE) -> #N/A | B83: =VLOOKUP($C83,'Variable Information'!$A$1:$C$480,3,FALSE) -> #N/A | D83: 2 | E83: Leinster
A84: =VLOOKUP($C84,'Variable Information'!$A$2:$E$480,5,FALSE) -> #N/A | B84: =VLOOKUP($C84,'Variable Information'!$A$1:$C$480,3,FALSE) -> #N/A | D84: 3 | E84: Munster
A85: =VLOOKUP($C85,'Variable Information'!$A$2:$E$480,5,FALSE) -> #N/A | B85: =VLOOKUP($C85,'Variable Information'!$A$1:$C$480,3,FALSE) -> #N/A | D85: 4 | E85: Ulster/Connacht
A86: =VLOOKUP($C86,'Variable Information'!$A$2:$E$480,5,FALSE) -> tenant | B86: =VLOOKUP($C86,'Variable Information'!$A$1:$C$480,3,FALSE) -> Q23_1. Are you currently or previously have been in the past two years...? - A tenant | C86: q23_1_1 | D86: 1 | E86: Yes
A87: =VLOOKUP($C87,'Variable Information'!$A$2:$E$480,5,FALSE) -> #N/A | B87: =VLOOKUP($C87,'Variable Information'!$A$1:$C$480,3,FALSE) -> #N/A | D87: 2 | E87: No
A88: =VLOOKUP($C88,'Variable Information'!$A$2:$E$480,5,FALSE) -> landlord | B88: =VLOOKUP($C88,'Variable Information'!$A$1:$C$480,3,FALSE) -> Q23_1. Are you currently or previously have been in the past two years...? - A landlord | C88: q23_1_2 | D88: 1 | E88: Yes
A89: =VLOOKUP($C89,'Variable Information'!$A$2:$E$480,5,FALSE) -> #N/A | B89: =VLOOKUP($C89,'Variable Information'!$A$1:$C$480,3,FALSE) -> #N/A | D89: 2 | E89: No
A90: =VLOOKUP($C90,'Variable Information'!$A$2:$E$480,5,FALSE) -> home_owner | B90: =VLOOKUP($C90,'Variable Information'!$A$1:$C$480,3,FALSE) -> Q23_1. Are you currently or previously have been in the past two years...? - A home-owner | C90: q23_1_3 | D90: 1 | E90: Yes
A91: =VLOOKUP($C91,'Variable Information'!$A$2:$E$480,5,FALSE) -> #N/A | B91: =VLOOKUP($C91,'Variable Information'!$A$1:$C$480,3,FALSE) -> #N/A | D91: 2 | E91: No
A92: =VLOOKUP($C92,'Variable Information'!$A$2:$E$480,5,FALSE) -> AJP_A1 | B92: =VLOOKUP($C92,'Variable Information'!$A$1:$C$480,3,FALSE) -> Q23_2_1_1. Issues experienced - Including issues with buying or selling property and disputes over title or ownership boundary locations and rights of way and Land Registry matters | C92: q23_2_01_1 | D92: 1 | E92: Yes
A93: =VLOOKUP($C93,'Variable Information'!$A$2:$E$480,5,FALSE) -> #N/A | B93: =VLOOKUP($C93,'Variable Information'!$A$1:$C$480,3,FALSE) -> #N/A | D93: 2 | E93: No
A94: =VLOOKUP($C94,'Variable Information'!$A$2:$E$480,5,FALSE) -> #N/A | B94: =VLOOKUP($C94,'Variable Information'!$A$1:$C$480,3,FALSE) -> #N/A | D94: 3 | E94: Prefer not to say
A95: =VLOOKUP($C95,'Variable Information'!$A$2:$E$480,5,FALSE) -> AJP_B1 | B95: =VLOOKUP($C95,'Variable Information'!$A$1:$C$480,3,FALSE) -> Q23_2_2_1. Issues experienced - Disputes about maintenance including of boundaries trees gardens | C95: q23_2_02_1 | D95: 1 | E95: Yes
A96: =VLOOKUP($C96,'Variable Information'!$A$2:$E$480,5,FALSE) -> #N/A | B96: =VLOOKUP($C96,'Variable Information'!$A$1:$C$480,3,FALSE) -> #N/A | D96: 2 | E96: No
A97: =VLOOKUP($C97,'Variable Information'!$A$2:$E$480,5,FALSE) -> #N/A | B97: =VLOOKUP($C97,'Variable Information'!$A$1:$C$480,3,FALSE) -> #N/A | D97: 3 | E97: Prefer not to say
A98: =VLOOKUP($C98,'Variable Information'!$A$2:$E$480,5,FALSE) -> AJP_B2 | B98: =VLOOKUP($C98,'Variable Information'!$A$1:$C$480,3,FALSE) -> Q23_2_2_2. Issues experienced - Problems or disputes to do with noise animals or unpleasant behaviour | C98: q23_2_02_2 | D98: 1 | E98: Yes
A99: =VLOOKUP($C99,'Variable Information'!$A$2:$E$480,5,FALSE) -> #N/A | B99: =VLOOKUP($C99,'Variable Information'!$A$1:$C$480,3,FALSE) -> #N/A | D99: 2 | E99: No
A100: =VLOOKUP($C100,'Variable Information'!$A$2:$E$480,5,FALSE) -> #N/A | B100: =VLOOKUP($C100,'Variable Information'!$A$1:$C$480,3,FALSE) -> #N/A | D100: 3 | E100: Prefer not to say
A101: =VLOOKUP($C101,'Variable Information'!$A$2:$E$480,5,FALSE) -> AJP_B3 | B101: =VLOOKUP($C101,'Variable Information'!$A$1:$C$480,3,FALSE) -> Q23_2_2_3. Issues experienced - Other disputes with neighbours such as issues with parking | C101: q23_2_02_3 | D101: 1 | E101: Yes
A102: =VLOOKUP($C102,'Variable Information'!$A$2:$E$480,5,FALSE) -> #N/A | B102: =VLOOKUP($C102,'Variable Information'!$A$1:$C$480,3,FALSE) -> #N/A | D102: 2 | E102: No
A103: =VLOOKUP($C103,'Variable Information'!$A$2:$E$480,5,FALSE) -> #N/A | B103: =VLOOKUP($C103,'Variable Information'!$A$1:$C$480,3,FALSE) -> #N/A | D103: 3 | E103: Prefer not to say
A104: =VLOOKUP($C104,'Variable Information'!$A$2:$E$480,5,FALSE) -> AJP_C1 | B104: =VLOOKUP($C104,'Variable Information'!$A$1:$C$480,3,FALSE) -> Q23_2_3_1. Issues experienced - Problems or disputes with your landlord over your rent or return of deposit | C104: q23_2_03_1 | D104: 1 | E104: Yes
A105: =VLOOKUP($C105,'Variable Information'!$A$2:$E$480,5,FALSE) -> #N/A | B105: =VLOOKUP($C105,'Variable Information'!$A$1:$C$480,3,FALSE) -> #N/A | D105: 2 | E105: No
A106: =VLOOKUP($C106,'Variable Information'!$A$2:$E$480,5,FALSE) -> #N/A | B106: =VLOOKUP($C106,'Variable Information'!$A$1:$C$480,3,FALSE) -> #N/A | D106: 3 | E106: Prefer not to say
A107: =VLOOKUP($C107,'Variable Information'!$A$2:$E$480,5,FALSE) -> AJP_C2 | B107: =VLOOKUP($C107,'Variable Information'!$A$1:$C$480,3,FALSE) -> Q23_2_3_2. Issues experienced - Problem with your landlord about the condition of your accommodation including damage/repairs | C107: q23_2_03_2 | D107: 1 | E107: Yes
A108: =VLOOKUP($C108,'Variable Information'!$A$2:$E$480,5,FALSE) -> #N/A | B108: =VLOOKUP($C108,'Variable Information'!$A$1:$C$480,3,FALSE) -> #N/A | D108: 2 | E108: No
A109: =VLOOKUP($C109,'Variable Information'!$A$2:$E$480,5,FALSE) -> #N/A | B109: =VLOOKUP($C109,'Variable Information'!$A$1:$C$480,3,FALSE) -> #N/A | D109: 3 | E109: Prefer not to say
A110: =VLOOKUP($C110,'Variable Information'!$A$2:$E$480,5,FALSE) -> AJP_C3 | B110: =VLOOKUP($C110,'Variable Information'!$A$1:$C$480,3,FALSE) -> Q23_2_3_3. Issues experienced - Eviction or threats of eviction or other harassment by a landlord | C110: q23_2_03_3 | D110: 1 | E110: Yes
A111: =VLOOKUP($C111,'Variable Information'!$A$2:$E$480,5,FALSE) -> #N/A | B111: =VLOOKUP($C111,'Variable Information'!$A$1:$C$480,3,FALSE) -> #N/A | D111: 2 | E111: No
A112: =VLOOKUP($C112,'Variable Information'!$A$2:$E$480,5,FALSE) -> #N/A | B112: =VLOOKUP($C112,'Variable Information'!$A$1:$C$480,3,FALSE) -> #N/A | D112: 3 | E112: Prefer not to say
A113: =VLOOKUP($C113,'Variable Information'!$A$2:$E$480,5,FALSE) -> AJP_D1 | B113: =VLOOKUP($C113,'Variable Information'!$A$1:$C$480,3,FALSE) -> Q23_2_4_1. Issues experienced - Issues with a tenant such as delayed/no payment of rent or dispute over a deposit | C113: q23_2_04_1 | D113: 1 | E113: Yes
...
